{
  "cname": "导航二级组合方式",
  "styleId": "e_navigationC",
  "styleClass": "",
  "tmpl": "<div class=\"${elemId} ${styleClass}\" needjs=\"true\">\r\n    {{#if ${dataList}}}\r\n    <div class=\"p_navButton\">\r\n        <p class=\"p_iconBox\">\r\n            {{{${menu}}}}\r\n            {{{${close}}}}\r\n        </p>\r\n    </div>\r\n    <ul class=\"p_navBox1\">\r\n        {{#each ${dataList}}}\r\n        <li class=\"border-bottom p_navItem1 \">\r\n            <p class=\"p_navCon s_templatetitle \">\r\n                <a href=\"{{#if url}}{{url}}{{^}}javascript:;{{/if}}\" {{#if url}}target=\"{{#eq target 'blank'}}_blank{{/eq}}\"{{/if}}>\r\n                    <span>{{navName}}</span>\r\n                </a>\r\n                {{#if children}}{{{../${arrow}}}}{{/if}}\r\n            </p>\r\n            {{#if children}}\r\n            <div class=\"p_navBox2\">\r\n                <div>\r\n                    <div class=\"p_imgBox\">\r\n                        {{#each children}}\r\n                            <span class=\"p_img\">{{#if img}}{{{nLazyImage img navName 'true'}}}{{/if}}</span>\r\n                        {{/each}}\r\n                    </div>\r\n                    <ul>\r\n                        {{#each children}}\r\n                        <li class=\"p_navItem2\">\r\n                            <p class=\"s_templatesum\">\r\n                                <a href=\"{{#if url}}{{url}}{{^}}javascript:;{{/if}}\" {{#if url}}target=\"{{#eq target 'blank'}}_blank{{/eq}}\"{{/if}}>\r\n                                    <span>{{navName}}</span>\r\n                                </a>\r\n                            </p>\r\n                        </li>\r\n                        {{/each}}\r\n                    </ul>\r\n                </div>\r\n            </div>\r\n            {{/if}}\r\n        </li>\r\n        {{/each}}\r\n    </ul>\r\n    {{^}}\r\n    {{{nNoDataPrompt ${i18n.noData}}}}\r\n    {{/if}}\r\n</div>",
  "css": [
    {
      "media": "",
      "cssText": ".e_navigationC .p_navItem1{\r\n    line-height: 1; \r\n}\r\n.e_navigationC .p_iconBox{\r\n    height: 45px;\r\n    width: 45px;\r\n    background: rgba(0,0,0,.1);\r\n    border-radius: 4px;\r\n    margin: 0px 15px 0 0;\r\n    display: flex;\r\n    flex-direction: column;\r\n    justify-content: center;\r\n}\r\n.e_navigationC .p_openIcon, \r\n.e_navigationC .p_closeIcon{\r\n    width: 100%;\r\n    height: 23px;\r\n}\r\n.e_navigationC .p_navButton{\r\n    display: none;\r\n}"
    },
    {
      "media": "screen and (max-width:768px)",
      "cssText": ".e_navigationC .p_navButton{\r\n    display: flex; \r\n    justify-content: flex-end;\r\n    padding: 18px 0;\r\n}\r\n.e_navigationC .p_navBox1{\r\n    display: none;\r\n    height: calc(100vh - 80px);\r\n    position: fixed;\r\n    top: 80px;\r\n    left: 0;\r\n    right: 0;\r\n    background: #fbfbfb;\r\n    padding: 15px;\r\n    z-index: 99;\r\n}\r\n.e_navigationC .p_navBox2{ \r\n   display: none;\r\n   padding-bottom: 20px;\r\n}\r\n.e_navigationC .p_navItem2 a{\r\n    color: rgb(0 0 0 / 40%);\r\n    line-height: 2;\r\n    transition: all ease .3s;\r\n}\r\n.e_navigationC .p_navItem2 a:hover{\r\n    color: #000;\r\n}\r\n.e_navigationC .p_navItem1{ \r\n    padding: 0;\r\n    border-bottom: 1px solid rgba(0,0,0,.5);\r\n }\r\n .e_navigationC .p_navCon {\r\n    display: flex;\r\n    justify-content: space-between;\r\n }\r\n .e_navigationC .p_navCon a{\r\n    line-height: 60px;\r\n    font-size: 15px;\r\n }\r\n.e_navigationC .p_navItem2{ \r\n    border: none;\r\n}\r\n.e_navigationC .p_img{ \r\n    display: none;\r\n}\r\n.e_navigationC .p_jtIcon{ \r\n    float: right;\r\n    transition: 0.5s;\r\n    margin: 20px 0;\r\n    width: 40px;\r\n}\r\n.e_navigationC .p_jtHover {\r\n    transition: 0.5s;\r\n    transform: rotate(90deg);\r\n}\r\n.e_navigationC .p_closeIcon{ \r\n    display: none;\r\n    float: right;\r\n}\r\n.e_navigationC .p_closeIcon, .e_navigationC .p_openIcon{ \r\n    cursor: pointer;\r\n}\r\n.e_navigationC .p_imgBox{\r\n    display: none;\r\n}"
    },
    {
      "media": "screen and (min-width: 769px)",
      "cssText": ".e_navigationC .p_navBox1{\r\n    position: relative;\r\n    justify-content: flex-end;\r\n}\r\n.e_navigationC .p_navBox1, .e_navigationC .p_navBox2{\r\n    width: 100%;\r\n    display: flex;\r\n}\r\n.e_navigationC .p_navBox2{\r\n    position: absolute; \r\n    top: 100%;\r\n    left: 0;\r\n    padding: 30px 40px;\r\n    z-index: 99;\r\n    background: #f5f5f5;\r\n}\r\n.e_navigationC .p_navBox2 ul{\r\n    width: 60%;\r\n    display: flex;\r\n    flex-wrap: wrap;\r\n    align-content: flex-start;\r\n    position: relative;\r\n}\r\n.e_navigationC .p_imgBox{\r\n    width: 30%;\r\n    position: relative;\r\n    height: 150px;\r\n    background: rgba(0,0,0,.2);\r\n    overflow: hidden;\r\n}\r\n.e_navigationC .p_imgBox img{\r\n    width: 100%;\r\n    height: 100%;\r\n    object-fit: cover;\r\n}\r\n.e_navigationC .p_navItem1{ \r\n    border: none;\r\n}\r\n.e_navigationC .p_navCon{\r\n    position: relative;\r\n}\r\n.e_navigationC .p_navCon a{\r\n    display: block;\r\n    padding: 0 20px;\r\n}\r\n.e_navigationC .p_navCon::before{\r\n    content: \" \";\r\n    height: 3px;\r\n    width: 0;\r\n    background-color: #409eff;\r\n    position: absolute;\r\n    left: 0;\r\n    right: 0;\r\n    bottom: 0;\r\n    transition: width 0.5s ease;\r\n    margin: 0 auto;\r\n}\r\n.e_navigationC .p_navItem1:hover .p_navCon::before{\r\n    width: 100%;\r\n}\r\n.e_navigationC .p_navItem2{\r\n    line-height: 1;\r\n    width: auto;\r\n    margin: 0 30px 0 0;\r\n}\r\n.e_navigationC .p_navItem2:hover{ \r\n\r\n}\r\n.e_navigationC .p_navItem2 span{\r\n    line-height: 1;\r\n    transition: all ease .3s;\r\n    opacity: .6;\r\n}\r\n.e_navigationC .p_navItem2:hover span{\r\n    opacity: 1;\r\n}\r\n.e_navigationC p{\r\n    display: flex;\r\n    flex-direction: column;\r\n    align-items: center;\r\n}\r\n.e_navigationC span{\r\n    text-align: center;\r\n    font-size: 16px;\r\n    line-height: 100px;\r\n    display: block;\r\n}\r\n.e_navigationC .p_img{\r\n    position: absolute;\r\n    left: 50%;\r\n    top: 50%;\r\n    transform: translate(-50%,-50%);\r\n    height: 100%;\r\n    width: auto;\r\n}\r\n.e_navigationC .p_jtIcon{\r\n    display: none;\r\n}\r\n.e_navigationC .p_iconBox{\r\n    display: none;\r\n}\r\n.e_navigationC .p_navBox2 > div{\r\n    width: 100%;\r\n    max-width: 900px;\r\n    margin: 0 auto;\r\n    display: flex;\r\n    justify-content: space-between;\r\n}\r\n.e_navigationC .p_navBox2 ul::after{\r\n    content: '';\r\n    border-left: 1px solid rgba(0, 0, 0, .1);\r\n    position: absolute;\r\n    top: -2px;\r\n    bottom: -2px;\r\n    left: -45px;\r\n    z-index: 2;\r\n    width: 1px;\r\n}"
    },
    {
      "media": "screen and (max-width: 1024px) and (min-width: 769px)",
      "cssText": ""
    }
  ],
  "prop": {
    "dataList": [
      {
        "navName": "首页"
      },
      {
        "navName": "公司概况",
        "children": [
          {
            "navName": "企业介绍"
          },
          {
            "navName": "发展历程"
          },
          {
            "navName": "关于我们"
          }
        ]
      },
      {
        "navName": "我们的产品"
      },
      {
        "navName": "新闻资讯",
        "children": [
          {
            "imgUrl": "https://img.alicdn.com/imgextra/i4/29242799/O1CN01OjRIlM1WXzH2opoIU_!!0-saturn_solar.jpg_468x468q75.jpg_.webp",
            "navName": "最新动态"
          },
          {
            "navName": "企业新闻"
          },
          {
            "navName": "行业新闻"
          }
        ]
      },
      {
        "navName": "招商加盟",
        "children": [
          {
            "navName": "合作伙伴"
          },
          {
            "navName": "加入我们"
          }
        ]
      },
      {
        "navName": "售后服务",
        "children": [
          {
            "navName": "服务宗旨"
          },
          {
            "navName": "在线咨询"
          },
          {
            "navName": "常见问题",
            "children": [
              {
                "navName": "生活常识"
              },
              {
                "navName": "百度百科"
              }
            ]
          },
          {
            "navName": "用户协议"
          }
        ]
      },
      {
        "navName": "联系我们",
        "children": [
          {
            "navName": "在线留言"
          },
          {
            "navName": "联系我们"
          }
        ]
      }
    ],
    "arrow": "<svg t=\"1625735163067\" class=\"icon p_jtIcon\" viewBox=\"0 0 1024 1024\" version=\"1.1\" xmlns=\"http://www.w3.org/2000/svg\" p-id=\"1486\" width=\"200\" height=\"200\"><path d=\"M661.16183428 486.94732961L415.99871022 219.24359155c-13.37500289-14.59708438-35.98351032-15.54759219-50.51270128-2.24048272-14.59708438 13.37500289-15.54759219 35.98351032-2.24048272 50.51270127l223.09776396 243.60157549-222.89408371 244.28050967c-13.30710947 14.59708438-12.28870823 37.20559179 2.30837613 50.51270125 14.59708438 13.30710947 37.20559179 12.28870823 50.51270128-2.30837613l244.75576356-268.11109855c0.47525392-0.54314733 1.01840124-1.15418807 1.42576173-1.6973354 11.13452018-13.51078973 10.93083994-33.53934734-1.2899749-46.84645682z\" p-id=\"1487\"></path></svg>",
    "menu": "<svg t=\"1625644785779\" class=\"icon p_openIcon\" viewBox=\"0 0 1024 1024\" version=\"1.1\" xmlns=\"http://www.w3.org/2000/svg\" p-id=\"5036\" width=\"200\" height=\"200\"><path d=\"M793.93115234 342.36010742H230.21716308c-18.58886719 0-33.65112305-14.75738526-33.65112304-32.95898437s15.0704956-32.95898438 33.65112305-32.95898438h563.71398925c18.58886719 0 33.65112305 14.75738526 33.65112305 32.95898438 0 18.20983887-15.0704956 32.95898438-33.65112305 32.95898437zM793.93115234 732.80047607H230.21716308c-18.58886719 0-33.65112305-14.75738526-33.65112304-32.95898437s15.0704956-32.95898438 33.65112305-32.95898438h563.71398925c18.58886719 0 33.65112305 14.75738526 33.65112305 32.95898438s-15.0704956 32.95898438-33.65112305 32.95898437zM793.93115234 537.99639893H230.21716308c-18.58886719 0-33.65112305-14.75738526-33.65112304-32.95898438s15.0704956-32.95898438 33.65112305-32.95898437h563.71398925c18.58886719 0 33.65112305 14.75738526 33.65112305 32.95898437s-15.0704956 32.95898438-33.65112305 32.95898438z\" p-id=\"5037\"></path></svg>",
    "close": "<svg t=\"1625645389126\" class=\"icon p_closeIcon\" viewBox=\"0 0 1024 1024\" version=\"1.1\" xmlns=\"http://www.w3.org/2000/svg\" p-id=\"5167\" width=\"200\" height=\"200\"><path d=\"M798.72 225.73511147a44.78293333 44.78293333 0 0 0-31.85777813-13.19822294c-11.83288853 0-23.66577813 5.00622187-31.85777707 13.19822294L512 447.82933333 289.45066667 225.28a44.78293333 44.78293333 0 0 0-31.85777814-13.19822187c-11.83288853 0-23.66577813 5.00622187-32.31288853 13.19822187a45.32906667 45.32906667 0 0 0 0 64.17066667L447.82933333 512 225.28 734.54933333a45.32906667 45.32906667 0 1 0 64.17066667 64.17066667L512 576.17066667l222.54933333 222.54933333a45.32906667 45.32906667 0 1 0 64.17066667-64.17066667L576.17066667 512l222.54933333-222.54933333c17.29422187-17.29422187 17.29422187-46.42133333 0-63.7155552z\" p-id=\"5168\"></path></svg>",
    "showArrow": true
  },
  "i18n": {
    "zh_CN": {
      "noData": "暂无数据"
    }
  },
  "datasource": "prop",
  "dataFields": {
    "dataList": "dataList",
    "arrow": "arrow",
    "menu": "menu",
    "close": "close",
    "showArrow": "showArrow"
  },
  "dataManage": {}
}