{
  "cname": "文字",
  "styleId": "e_text",
  "styleClass": "s_title",
  "tmpl": "<p class=\"${elemId} ${styleClass}\">\n    {{#if ${href}.value}}\n        <a href=\"{{$transferLink ${href} compId}}\" target=\"{{${href}.target}}\">\n    {{/if}}\n    {{${text}}}\n    {{#if ${href}.value}}\n        </a>\n    {{/if}}\n</p>",
  "css": [
    {
      "media": "",
      "cssText": ".e_text{\n\n}\n"
    },
    {
      "media": "screen and (max-width:768px)",
      "cssText": ""
    },
    {
      "media": "screen and (min-width: 769px)",
      "cssText": ""
    },
    {
      "media": "screen and (max-width: 1024px) and (min-width: 769px)",
      "cssText": ""
    }
  ],
  "prop": {
    "text": "这里是占位文字",
    "href": {
      "type": "none",
      "value": "",
      "target": ""
    }
  },
  "i18n": {
    "zh_CN": {}
  },
  "datasource": "prop",
  "dataFields": {
    "text": "text",
    "href": "href"
  }
}